[
  {
    "_id": "6072d4e83abd910cb7358aad",
    "orderItems": [
      {
        "quantity": 3,
        "product": "5f15d8852a025143f9593a7c"
      },
      {
        "quantity": 1,
        "product": "5f15d9b3e520d44421ed8e9d"
      }
    ],
    "shippingAddress1": "Flowers Street",
    "shippingAddress2": "13",
    "city": "Prague",
    "zip": "15541",
    "country": "Czech Republic",
    "phone": "688874451",
    "totalPrice": 1240.9,
    "user": "6268359aa7ec003a1862541a"
  },
  {
    "_id": "609d7eea3373711346c5e953",
    "orderItems": [
      {
        "quantity": 7,
        "product": "5f68fd316170530b7e0afc54"
      },
      {
        "quantity": 4,
        "product": "5f15da13e520d44421ed8e9e"
      }
    ],
    "shippingAddress1": "Street 1",
    "shippingAddress2": "Apartment1",
    "city": "City",
    "zip": "151222",
    "country": "BR",
    "phone": "(123) 456-7899",
    "totalPrice": 4161,
    "user": "6268359aa7ec003a1862541a"
  },
  {
    "_id": "609d874d3373711346c5e956",
    "orderItems": [
      {
        "quantity": 7,
        "product": "5f68fd316170530b7e0afc54"
      },
      {
        "quantity": 4,
        "product": "5f15da13e520d44421ed8e9e"
      }
    ],
    "shippingAddress1": "street2",
    "shippingAddress2": "aprtment2",
    "city": "city",
    "zip": "12222",
    "country": "CX",
    "phone": "(123) 456-7777",
    "totalPrice": 4161,
    "user": "6268359aa7ec003a1862541a"
  },
  {
    "_id": "609d898d3373711346c5e959",
    "orderItems": [
      {
        "quantity": 7,
        "product": "5f68fd316170530b7e0afc54"
      },
      {
        "quantity": 4,
        "product": "5f15da13e520d44421ed8e9e"
      }
    ],
    "shippingAddress1": "Street 1",
    "shippingAddress2": "Apartment 1",
    "city": "City 1",
    "zip": "155555",
    "country": "AT",
    "phone": "(123) 456-7888",
    "totalPrice": 4161,
    "user": "6268359aa7ec003a1862541a"
  },
  {
    "_id": "609d8a0c3373711346c5e95c",
    "orderItems": [
      {
        "quantity": 1,
        "product": "5f15da135420d44443ed8e9e"
      },
      {
        "quantity": 1,
        "product": "5f15da135420d44456ed8e9e"
      }
    ],
    "shippingAddress1": "Street 1",
    "shippingAddress2": "Apartment 1",
    "city": "City",
    "zip": "1111",
    "country": "AT",
    "phone": "(123) 456-7777",
    "totalPrice": 1260,
    "user": "6268359aa7ec003a1862541a"
  }
]
